mvat/__init__.py
mvat/foo.py
mvat-0.0.3.dist-info/METADATA
mvat-0.0.3.dist-info/WHEEL
mvat-0.0.3.dist-info/RECORD
