Metadata-Version: 2.4
Name: mvat
Version: 0.0.3
Summary: mvat
Project-URL: Homepage, https://Jordan-Pierce.github.io/mvat/
Project-URL: Repository, https://github.com/Jordan-Pierce/mvat
Project-URL: Documentation, https://Jordan-Pierce.github.io/mvat/
Author-email: Jordan Pierce <jordanpatrickpierce@gmail.com>
Keywords: python
Classifier: Intended Audience :: Developers
Classifier: Programming Language :: Python
Classifier: Programming Language :: Python :: 3
Classifier: Programming Language :: Python :: 3.9
Classifier: Programming Language :: Python :: 3.10
Classifier: Programming Language :: Python :: 3.11
Classifier: Programming Language :: Python :: 3.12
Classifier: Programming Language :: Python :: 3.13
Classifier: Topic :: Software Development :: Libraries :: Python Modules
Requires-Python: <4.0,>=3.9
